grafana_loki_provider/__init__.py
grafana_loki_provider/hooks/__init__.py
grafana_loki_provider/hooks/loki.py
grafana_loki_provider/log/__init__.py
grafana_loki_provider/log/loki_task_handler.py
airflow_provider_grafana_loki-0.0.2.dist-info/METADATA
airflow_provider_grafana_loki-0.0.2.dist-info/WHEEL
airflow_provider_grafana_loki-0.0.2.dist-info/entry_points.txt
airflow_provider_grafana_loki-0.0.2.dist-info/licenses/LICENSE.txt
airflow_provider_grafana_loki-0.0.2.dist-info/RECORD
