Metadata-Version: 2.1
Name: airflow-provider-grafana-loki
Version: 0.0.2
Summary: A provider package for pushing and reading airflow task log from Grafana Loki.
Project-URL: Homepage, http://grafana.com/
Author-email: Snjypl <toepoe.py@gmail.com>
License-File: LICENSE.txt
Classifier: Framework :: Apache Airflow
Classifier: Framework :: Apache Airflow :: Provider
Requires-Python: ~=3.7
Requires-Dist: apache-airflow>=2.0.0
Provides-Extra: test
Requires-Dist: pytest-mock; extra == 'test'
Requires-Dist: pytest>=7.0.0; extra == 'test'
Requires-Dist: requests-mock; extra == 'test'
